BioML/__init__.py
BioML/main.py
BioProt/__init__.py
BioProt/main.py
BioProt-0.2.0.dist-info/LICENSE
BioProt-0.2.0.dist-info/METADATA
BioProt-0.2.0.dist-info/WHEEL
BioProt-0.2.0.dist-info/entry_points.txt
BioProt-0.2.0.dist-info/top_level.txt
BioProt-0.2.0.dist-info/RECORD
